plexfuse/TimeoutLock.py
plexfuse/__main__.py
plexfuse/__version__.py
plexfuse/measure_speed.py
plexfuse/normalize.py
plexfuse/cache/CacheControl.py
plexfuse/cache/CachedPropertyCacheControl.py
plexfuse/cache/DelayedPropertyCacheControl.py
plexfuse/cache/FileCache.py
plexfuse/cache/HttpCache.py
plexfuse/cache/UserDictCacheControl.py
plexfuse/control/Control.py
plexfuse/control/ControlListener.py
plexfuse/control/ControlVFS.py
plexfuse/fs/FsOptions.py
plexfuse/fs/PlexDirectory.py
plexfuse/fs/PlexFS.py
plexfuse/fs/PlexFile.py
plexfuse/fs/RefCountedDict.py
plexfuse/fs/Timestampable.py
plexfuse/fs/main.py
plexfuse/fs/plex_errno.py
plexfuse/fs/retry.py
plexfuse/plex/Monitor.py
plexfuse/plex/PlexApi.py
plexfuse/plex/types.py
plexfuse/sentry/__init__.py
plexfuse/sentry/sentry.py
plexfuse/vfs/ChunkedFile.py
plexfuse/vfs/Playable.py
plexfuse/vfs/PlexVFS.py
plexfuse/vfs/entry/AttrEntry.py
plexfuse/vfs/entry/ControlSockEntry.py
plexfuse/vfs/entry/DirEntry.py
plexfuse/vfs/entry/EpisodeEntry.py
plexfuse/vfs/entry/FileEntry.py
plexfuse/vfs/entry/LibraryEntry.py
plexfuse/vfs/entry/MovieEntry.py
plexfuse/vfs/entry/PathEntry.py
plexfuse/vfs/entry/PlexMatchEntry.py
plexfuse/vfs/entry/SeasonEntry.py
plexfuse/vfs/entry/SectionEntry.py
plexfuse/vfs/entry/SubtitleEntry.py
plexfuse/vfs/entry/SymlinkEntry.py
plex_fuse-0.11.1.dist-info/LICENSE
plex_fuse-0.11.1.dist-info/METADATA
plex_fuse-0.11.1.dist-info/WHEEL
plex_fuse-0.11.1.dist-info/entry_points.txt
plex_fuse-0.11.1.dist-info/top_level.txt
plex_fuse-0.11.1.dist-info/RECORD
