Metadata-Version: 2.1
Name: plex-fuse
Version: 0.11.1
Summary: Plex FUSE Filesystem - Mount Remote Plex Media Server contents as local filesystem
Author-email: Elan Ruusamäe <glen@pld-linux.org>
License: BSD 3-Clause License
Project-URL: Homepage, https://github.com/glensc/plex-fuse
Project-URL: Documentation, https://github.com/glensc/plex-fuse#plex-fuse-filesystem
Project-URL: Repository, https://github.com/glensc/plex-fuse
Project-URL: Issues, https://github.com/glensc/plex-fuse/issues
Project-URL: Changelog, https://github.com/glensc/plex-fuse/releases
Keywords: fuse,filesystem,fs,plex,fuse-filesystem,user-space
Classifier: Development Status :: 3 - Alpha
Classifier: Intended Audience :: End Users/Desktop
Classifier: Topic :: System :: Filesystems
Classifier: Topic :: Multimedia :: Video :: Display
Classifier: License :: OSI Approved :: BSD License
Classifier: Programming Language :: Python :: 3
Classifier: Programming Language :: Python :: 3.11
Classifier: Programming Language :: Python :: 3.12
Requires-Python: >=3.11
License-File: LICENSE
Requires-Dist: fuse-python
Requires-Dist: humanize>=4.9.0
Requires-Dist: plexapi>=4.15
Requires-Dist: requests-cache>=1.1
Requires-Dist: websocket-client>=1.7.0
